tempfileatexit/__init__.py
tempfileatexit-0.0.3.dist-info/LICENSE
tempfileatexit-0.0.3.dist-info/METADATA
tempfileatexit-0.0.3.dist-info/WHEEL
tempfileatexit-0.0.3.dist-info/top_level.txt
tempfileatexit-0.0.3.dist-info/RECORD
