Metadata-Version: 2.1
Name: tempfileatexit
Version: 0.0.3
Summary: Remove tempory files at program exit, combination of tempfile and atexit should be as simple as possible.
Home-page: https://github.com/jachym/tempfileatexit
Author: Jachym Cepicky
Author-email: jachym@cepicky.ch
License: UNKNOWN
Platform: UNKNOWN
Classifier: Programming Language :: Python :: 3
Classifier: License :: OSI Approved :: MIT License
Classifier: Operating System :: OS Independent
Requires-Python: >=3.0
